{ 	"code"    : "TA2016",
	"name"    : "תל אביב 2016",
	"source"  : "מודל תל אביב",
	"dir"     : "TA2016",
	"tazlyr"  : "TAZ_v41",
	"tazvar"  : "TAZV41",
	"tazfile" : "TAZ_v41.geojson",
	"file"    : "TA2016.csv",
	"scenarios" : {
		"base": {
			"desc": "תרחיש בסיס",
			"years": [ 2017, 2025, 2030, 2040 ] }
	},
	"ag" : [ 
		{ "lyr": "napot",        "var":"nafanum"   },  
		{ "lyr": "MetroSec2008", "var":"full_code" }  
		],
	"dict": {
			"scenario":        { "group": "זיהוי", "type": "character", "mode": "category", "bank": "scenario", "description": "תרחיש"},
			"year":            { "group": "זיהוי", "type": "integer", "mode": "discrete", "bank": "year", "description": "שנת יעד"},
			"taz":             { "group": "זיהוי", "type": "integer", "mode": "continous", "bank": "taz", "description": "אזור תנועה"},
			"area":            { "group": "לא בשימוש", "type": "real", "mode": "continous", "description": "שטח"},
			"type":            { "group": "שימושי קרקע", "type": "integer", "mode": "category", "description": "סוג עיקרי של האזור",
			            "Values": [
			                {"value": 1, "label": "Metropolitan CBD"},
			                {"value": 2, "label": "Urban Residential low-density"},
			                {"value": 3, "label": "Urban Residential high-density"},
			                {"value": 4, "label": "Major public institutions"},
			                {"value": 5, "label": "Commercial"},
			                {"value": 6, "label": "Major Employment centers"},
			                {"value": 7, "label": "Medium Employment centers"},
			                {"value": 8, "label": "Mixed Use Areas"},
			                {"value": 9, "label": "Major Transport facilities"},
			                {"value": 10, "label": "Sports and Tourism"},
			                {"value": 11, "label": "Rural Areas"},
			                {"value": 12, "label": "Open Areas"},
			                {"value": 13, "label": "Military Areas"},
			                {"value": 14, "label": "Cemetery"},
			                {"value": 15, "label": "Small Settlements"}
			       		     ]
			},
			"cultural":        { "group": "שימושי קרקע", "type": "integer", "mode": "category", "description": "שימושי קרקע תרבות",
			            "Values": [
			                {"value": 0, "label": "none"},
			                {"value": 1, "label": "Metropolitan Cultural area"},
			                {"value": 2, "label": "local Cultural area"}
			       		     ]
			},
			"education":       { "group": "שימושי קרקע", "type": "integer", "mode": "category", "description": "שימושי קרקע חינוך",
			            "Values": [
			                {"value": 0, "label": "none"},
			                {"value": 1, "label": "higher education: College, university"},
			                {"value": 2, "label": "high school"},
			                {"value": 3, "label": "elementary schools"}
			       		     ]
			},
			"office":          { "group": "שימושי קרקע", "type": "integer", "mode": "category", "description": "שימושי קרקע משרדים",
			            "Values": [
			                {"value": 0, "label": "none"},
			                {"value": 1, "label": "Major office concentrations"},
			                {"value": 2, "label": " Other zones with offices use (City center, commercial/industrial)"}
			       		     ]
			},
			"shopping":        { "group": "שימושי קרקע", "type": "integer", "mode": "category", "description": "שימושי קרקע קניות",
			            "Values": [
			                {"value": 0, "label": "none"},
			                {"value": 1, "label": " Shopping mall"},
			                {"value": 2, "label": " shopping streets"},
			                {"value": 3, "label": " Market"}
			       		     ]
			},
			"health":          { "group": "שימושי קרקע", "type": "integer", "mode": "category", "description": "שימושי קרקע בריאות",
			            "Values": [
			                {"value": 0, "label": "none"},
			                {"value": 1, "label": "hospitals"}
			       		     ]
			},
			"urban":           { "group": "שימושי קרקע", "type": "integer", "mode": "category", "description": "שימושי קרקע עירוני",
			            "Values": [
			                {"value": 0, "label": "none"},
			                {"value": 1, "label": "Cities over 20,000 inhabits"}
			       		     ]
			},
			"religiosit":      { "group": "שימושי קרקע", "type": "integer", "mode": "category", "description": "שימושי קרקע דתי",
			            "Values": [
			                {"value": 0, "label": "none"},
			                {"value": 1, "label": "Religious Jewish areas"},
			                {"value": 2, "label": "Religious Islamic areas"}
			       		     ]
			},
			"transporta":      { "group": "שימושי קרקע", "type": "integer", "mode": "category", "description": "שימושי קרקע תחבורה",
			            "Values": [
			                {"value": 0, "label": "none"},
			                {"value": 1, "label": "transportation facilities"}
			       		     ]
			},
			"empl_indu":       { "group": "מקומות עבודה", "type": "real", "mode": "continous", "description": "מועסקים בתעשייה"},
			"empl_comm":       { "group": "מקומות עבודה", "type": "real", "mode": "continous", "description": "מועסקים במסחר"},
			"empl_serv":       { "group": "מקומות עבודה", "type": "real", "mode": "continous", "description": "מועסקים בשרותים"},
			"empl_tot":        { "group": "מקומות עבודה", "type": "real", "mode": "continous", "bank": "employment", "description": "סה\"כ מועסקים"},
			"students":        { "group": "חינוך", "type": "real", "mode": "continous", "description": "סטודנטים", "comment": "שלומדים באזור"},
			"population":      { "group": "אוכלוסייה", "type": "real", "mode": "continous", "bank": "population", "description": "אוכלוסייה"},
			"households":      { "group": "משקי בית", "type": "real", "mode": "continous", "description": "משקי בית"},
			"parkcost":        { "group": "חניה", "type": "real", "mode": "continous", "description": "עלות חניה"},
			"parkwalk":        { "group": "חניה", "type": "real", "mode": "continous", "description": "זמן הליכה חניה"},
			"popdens":         { "group": "לא בשימוש", "type": "real", "mode": "continous", "description": "צפיפות אוכלוסייה", "comment": "1000 person/sq. Km"},
			"ga21":            { "group": "אוכלוסייה", "type": "real", "mode": "continous", "description": "נשים בגילאים 0-14"},
			"ga22":            { "group": "אוכלוסייה", "type": "real", "mode": "continous", "description": "נשים בגילאים 15-19"},
			"ga23":            { "group": "אוכלוסייה", "type": "real", "mode": "continous", "description": "נשים בגילאים 20-24"},
			"ga24":            { "group": "אוכלוסייה", "type": "real", "mode": "continous", "description": "נשים בגילאים 25-34"},
			"ga25":            { "group": "אוכלוסייה", "type": "real", "mode": "continous", "description": "נשים בגילאים 35-64"},
			"ga26":            { "group": "אוכלוסייה", "type": "real", "mode": "continous", "description": "נשים בגילאים 65+"},
			"ga11":            { "group": "אוכלוסייה", "type": "real", "mode": "continous", "description": "גברים  בגילאים 0-14"},
			"ga12":            { "group": "אוכלוסייה", "type": "real", "mode": "continous", "description": "גברים  בגילאים 15-19"},
			"ga13":            { "group": "אוכלוסייה", "type": "real", "mode": "continous", "description": "גברים  בגילאים 20-24"},
			"ga14":            { "group": "אוכלוסייה", "type": "real", "mode": "continous", "description": "גברים  בגילאים 25-34"},
			"ga15":            { "group": "אוכלוסייה", "type": "real", "mode": "continous", "description": "גברים  בגילאים 35-64"},
			"ga16":            { "group": "אוכלוסייה", "type": "real", "mode": "continous", "description": "גברים  בגילאים 65+"},
			"workers":         { "group": "כח עבודה", "type": "real", "mode": "continous", "description": "כח עבודה (מועסקים)"},
			"workperc":        { "group": "כח עבודה", "type": "real", "mode": "ratio", "description": "כח עבודה (מועסקים) / אוכלוסייה"},
			"avgHH":           { "group": "משקי בית", "type": "real", "mode": "average", "description": "גודל מ\"ב ממוצע"},
			"soceco":          { "group": "הכנסה", "type": "integer", "mode": "category", "description": "רמה חברתית כלכלית", "comment": "according to definition of NTA"},
			"Mlic2":           { "group": "רשיונות נהיגה", "type": "real", "mode": "continous", "description": "רשיונות נהיגה לנפש  גברים 15-19"},
			"Mlic3":           { "group": "רשיונות נהיגה", "type": "real", "mode": "continous", "description": "רשיונות נהיגה לנפש  גברים 20-24"},
			"Mlic4":           { "group": "רשיונות נהיגה", "type": "real", "mode": "continous", "description": "רשיונות נהיגה לנפש  גברים 25-34"},
			"Mlic5":           { "group": "רשיונות נהיגה", "type": "real", "mode": "continous", "description": "רשיונות נהיגה לנפש  גברים 35-64"},
			"Mlic6":           { "group": "רשיונות נהיגה", "type": "real", "mode": "continous", "description": "רשיונות נהיגה לנפש  גברים 65+"},
			"Flic2":           { "group": "רשיונות נהיגה", "type": "real", "mode": "continous", "description": "רשיונות נהיגה לנפש  נשים 15-19"},
			"Flic3":           { "group": "רשיונות נהיגה", "type": "real", "mode": "continous", "description": "רשיונות נהיגה לנפש  נשים 20-24"},
			"Flic4":           { "group": "רשיונות נהיגה", "type": "real", "mode": "continous", "description": "רשיונות נהיגה לנפש  נשים 25-34"},
			"Flic5":           { "group": "רשיונות נהיגה", "type": "real", "mode": "continous", "description": "רשיונות נהיגה לנפש  נשים 35-64"},
			"Flic6":           { "group": "רשיונות נהיגה", "type": "real", "mode": "continous", "description": "רשיונות נהיגה לנפש  נשים 65+"},
			"emp2pop":         { "group": "מקומות עבודה", "type": "real", "mode": "continous", "description": "יחס מועסקים לאוכלוסייה", "comment": "Employment/population ratio"},
			"parkcap":         { "group": "לא בשימוש", "type": "real", "mode": "continous", "description": "קיבולת חניה", "comment": "overall parking capacity"},
			"parkAM":          { "group": "לא בשימוש", "type": "real", "mode": "continous"},
			"parkPM":          { "group": "לא בשימוש", "type": "real", "mode": "continous"},
			"parkOP":          { "group": "לא בשימוש", "type": "real", "mode": "continous"},
			"INTLSUME":        { "group": "לא בשימוש", "type": "real", "mode": "continous"},
			"INTLSUMO":        { "group": "לא בשימוש", "type": "real", "mode": "continous"},
			"INTLSUMS":        { "group": "לא בשימוש", "type": "real", "mode": "continous"},
			"INTLSUMW":        { "group": "לא בשימוש", "type": "real", "mode": "continous"},
			"LSIZESEC":        { "group": "לא בשימוש", "type": "real", "mode": "continous"},
			"LSIZEINTS":       { "group": "לא בשימוש", "type": "real", "mode": "continous"},
			"LSUMSIZE0":       { "group": "לא בשימוש", "type": "real", "mode": "continous"},
			"LSUMSIZES":       { "group": "לא בשימוש", "type": "real", "mode": "continous"},
			"Hh0car":          { "group": "רמת מינוע", "type": "real", "mode": "continous", "description": "משקי בית עם 0 כ\"ר"},
			"HH1car":          { "group": "רמת מינוע", "type": "real", "mode": "continous", "description": "משקי בית עם 1 כ\"ר"},
			"HH2car":          { "group": "רמת מינוע", "type": "real", "mode": "continous", "description": "משקי בית עם 2 כ\"ר"},
			"HH3car":          { "group": "רמת מינוע", "type": "real", "mode": "continous", "description": "משקי בית עם 2+ כ\"ר"} },
	"geodict": {
			"TAZV41":          { "group": "זיהוי", "type": "integer", "mode": "discrete", "bank": "geotaz", "description": "אזור תנועה"},
			"SEMEL":           { "group": "זיהוי", "type": "integer", "mode": "discrete", "description": "סמל יישוב"},
			"NAME_H":          { "group": "זיהוי", "type": "character", "mode": "free", "description": "שם יישוב"},
			"MUNC_NAME":       { "group": "זיהוי", "type": "character", "mode": "free", "description": "שם רשות"},
			"TAZ_OLD":         { "group": "זיהוי", "type": "integer", "mode": "discrete", "description": "אזור תנועה ישן"},
			"GE":              { "group": "גיאוגרפיה", "type": "integer", "mode": "discrete", "description": "קוד גזרה"},
			"nafanum":         { "group": "גיאוגרפיה", "type": "integer", "mode": "discrete", "description": "מפסר נפה"},
			"Area":            { "group": "שטח", "type": "real", "mode": "continous", "bank": "area", "description": "שטח"} }
}
